blacebo/__init__.py
blacebo/client.py
blacebo/endpoint.py
blacebo/exceptions.py
blacebo/endpoints/__init__.py
blacebo/endpoints/data_view.py
blacebo/endpoints/data_view2.py
blacebo/endpoints/kb_settings.py
blacebo/endpoints/role.py
blacebo/endpoints/role_mapping.py
blacebo/endpoints/space.py
blacebo-0.0.1.dist-info/METADATA
blacebo-0.0.1.dist-info/WHEEL
blacebo-0.0.1.dist-info/licenses/LICENSE
blacebo-0.0.1.dist-info/RECORD
