Metadata-Version: 2.4
Name: blacebo
Version: 0.0.1
Summary: A elastic API wrapper.
Project-URL: Homepage, https://github.com/aruehl/blacebo
Project-URL: Issues, https://github.com/aruehl/blacebo/issues
Author-email: Andreas Rühl <blacebo@mail.knusel.me>
License-Expression: Apache-2.0
License-File: LICENSE
Classifier: Operating System :: OS Independent
Classifier: Programming Language :: Python :: 3
Requires-Python: >=3.9
